discord/ext/alternatives/__init__.py
discord/ext/alternatives/_common.py
discord/ext/alternatives/asset_converter.py
discord/ext/alternatives/binary_checks.py
discord/ext/alternatives/bot_send_help.py
discord/ext/alternatives/category_channel.py
discord/ext/alternatives/class_commands.py
discord/ext/alternatives/command_piping.py
discord/ext/alternatives/command_suffix.py
discord/ext/alternatives/converter_dict.py
discord/ext/alternatives/dict_converter.py
discord/ext/alternatives/fix_4098.py
discord/ext/alternatives/guild_converter.py
discord/ext/alternatives/inline_bot_commands.py
discord/ext/alternatives/int_map.py
discord/ext/alternatives/jump_url.py
discord/ext/alternatives/literal_converter.py
discord/ext/alternatives/material_colors.py
discord/ext/alternatives/material_colours.py
discord/ext/alternatives/menus_remove_reaction.py
discord/ext/alternatives/message_eq.py
discord/ext/alternatives/messageable_wait_for.py
discord/ext/alternatives/role.py
discord/ext/alternatives/silent_delete.py
discord/ext/alternatives/specific_error_handler.py
discord/ext/alternatives/subcommand_error.py
discord/ext/alternatives/webhook_channel.py
discord_ext_alternatives-2021.4.13.dist-info/LICENSE
discord_ext_alternatives-2021.4.13.dist-info/METADATA
discord_ext_alternatives-2021.4.13.dist-info/WHEEL
discord_ext_alternatives-2021.4.13.dist-info/top_level.txt
discord_ext_alternatives-2021.4.13.dist-info/RECORD
