Metadata-Version: 1.2
Name: discord-ext-alternatives
Version: 2021.4.13
Summary: A discord.py extension with additional and alternative features. Use with caution.
Home-page: https://github.com/Ext-Creators/discord-ext-alternatives
Author: Ext-Creators
License: Apache Software License
Project-URL: Issue Tracker, https://github.com/Ext-Creators/discord-ext-alternatives/issues
Project-URL: Source, https://github.com/Ext-Creators/discord-ext-alternatives
Platform: UNKNOWN
Classifier: Development Status :: 5 - Production/Stable
Classifier: Intended Audience :: Developers
Classifier: License :: OSI Approved :: Apache Software License
Classifier: Natural Language :: English
Classifier: Operating System :: OS Independent
Classifier: Programming Language :: Python :: 3
Classifier: Programming Language :: Python :: 3 :: Only
Classifier: Programming Language :: Python :: 3.5
Classifier: Programming Language :: Python :: 3.6
Classifier: Programming Language :: Python :: 3.7
Classifier: Programming Language :: Python :: 3.8
Classifier: Programming Language :: Python :: 3.9
Classifier: Programming Language :: Python :: Implementation :: CPython
Classifier: Topic :: Software Development
Classifier: Topic :: Software Development :: Libraries
Classifier: Topic :: Software Development :: Libraries :: Python Modules
Requires-Python: >=3.5.3
